baizhanMath2/__init__.py
baizhanMath2/demo1.py
baizhanMath2/demo2.py
LingYuMath2-1.0.dist-info/METADATA
LingYuMath2-1.0.dist-info/WHEEL
LingYuMath2-1.0.dist-info/top_level.txt
LingYuMath2-1.0.dist-info/RECORD
